{
  "teachers": [
    {
      "id": 1,
      "avatar_url": "https://cdn.awsli.com.br/600x700/1035/1035809/produto/38424928/a2686d2305.jpg",
      "name": "Rocketseat",
      "date_birth": "2000-12-30",
      "graduation": "doutorado",
      "type_class": "presential",
      "subjects": "Estude, Se Capacite, Seja um Foguete, Rocketseat, Matemática, Programação, Estude, Se Capacite, Seja um Foguete, Rocketseat, Matemática, Programação",
      "created_at": 1609283059600,
      "birth": null
    },
    {
      "id": 2,
      "avatar_url": "https://cdn.awsli.com.br/600x700/1035/1035809/produto/38424928/a2686d2305.jpg",
      "name": "Rocketstudy",
      "date_birth": "2000-12-30",
      "graduation": "doutorado",
      "type_class": "distance",
      "subjects": "Estude, Se Capacite, Seja um Foguete",
      "created_at": 1609283531775,
      "birth": null
    }
  ],
  "students": [
    {
      "id": 1,
      "avatar_url": "https://www.google.com",
      "name": "Google",
      "email": "google@gmail.com",
      "date_birth": 1580601600000,
      "school_formation": "2_ensino_medio",
      "carg_hour": "8"
    },
    {
      "id": 2,
      "avatar_url": "https://www.google.com",
      "name": "fegergerge",
      "email": "google@email.com",
      "date_birth": 1581379200000,
      "school_formation": "5_ensino_fundamental",
      "carg_hour": "4"
    }
  ]
}